llm2vec/__init__.py
llm2vec/experiment_utils.py
llm2vec/llm2vec.py
llm2vec/version.py
llm2vec/dataset/E5Data.py
llm2vec/dataset/Wiki1M.py
llm2vec/dataset/__init__.py
llm2vec/dataset/dataset.py
llm2vec/dataset/utils.py
llm2vec/loss/HardNegativeNLLLoss.py
llm2vec/loss/__init__.py
llm2vec/loss/loss_utils.py
llm2vec/loss/utils.py
llm2vec/models/__init__.py
llm2vec/models/attn_mask_utils.py
llm2vec/models/bidirectional_gemma.py
llm2vec/models/bidirectional_llama.py
llm2vec/models/bidirectional_mistral.py
llm2vec/models/bidirectional_qwen2.py
llm2vec-0.2.2.dist-info/LICENSE
llm2vec-0.2.2.dist-info/METADATA
llm2vec-0.2.2.dist-info/WHEEL
llm2vec-0.2.2.dist-info/top_level.txt
llm2vec-0.2.2.dist-info/RECORD
