Metadata-Version: 2.1
Name: llm2vec
Version: 0.2.2
Summary: The official llm2vec library
Home-page: https://github.com/McGill-NLP/llm2vec
Author: McGill NLP
Author-email: parishad.behnamghader@mila.quebec
License: MIT
Classifier: Programming Language :: Python :: 3
Classifier: Operating System :: OS Independent
Classifier: License :: OSI Approved :: MIT License
Requires-Python: >=3.8
License-File: LICENSE
Requires-Dist: numpy
Requires-Dist: tqdm
Requires-Dist: torch
Requires-Dist: peft
Requires-Dist: transformers (<=4.40.2,>=4.39.1)
Requires-Dist: datasets
Requires-Dist: evaluate
Requires-Dist: scikit-learn
Provides-Extra: evaluation
Requires-Dist: mteb (>=1.12.60) ; extra == 'evaluation'
